pulsar_data_collection/__init__.py
pulsar_data_collection/data_capture/__init__.py
pulsar_data_collection/data_capture/data_capture.py
pulsar_data_collection/data_capture/exceptions.py
pulsar_data_collection/db_connectors/influxdb/__init__.py
pulsar_data_collection/db_connectors/influxdb/config.py
pulsar_data_collection/db_connectors/influxdb/db_connection.py
pulsar_data_collection/db_connectors/influxdb/queries.py
pulsar_data_collection-0.1.1.dist-info/WHEEL
pulsar_data_collection-0.1.1.dist-info/METADATA
pulsar_data_collection-0.1.1.dist-info/RECORD
