Metadata-Version: 2.1
Name: pulsar-data-collection
Version: 0.1.1
Summary: sdk enabling data collection from model serving code for our MPM solution
Home-page: https://github.com/Rocket-Science-Development/pulsar_data_collection
License: MIT
Author: Pulsar team
Author-email: pulsar@data-rs.io
Requires-Python: >=3.9,<4.0
Classifier: License :: OSI Approved :: MIT License
Classifier: Programming Language :: Python :: 3
Classifier: Programming Language :: Python :: 3.9
Classifier: Programming Language :: Python :: 3.10
Classifier: Programming Language :: Python :: 3.11
Requires-Dist: SQLAlchemy (>=1.4.39,<2.0.0)
Requires-Dist: influxdb (==5.3.1)
Requires-Dist: influxdb-client[ciso] (>=1.31.0,<2.0.0)
Requires-Dist: pandas (>=1.4.2,<2.0.0)
Requires-Dist: pydantic (>=1.6.2,<2.0.0)
Requires-Dist: pysqlite3 (>=0.4.7,<0.5.0)
